MainAccesslib/__init__.py
MainAccesslib/ac_accesspoint.py
MainAccesslib/bc_accesspoint.py
MainAccesslib/comm_accesspoint.py
MainAccesslib/doc_operations.py
MainAccesslib/ex_accesspoint.py
MainAccesslib/global_constants.py
MainAccesslib/hearbeat_thread.py
MainAccesslib/characteritzation/__init__.py
MainAccesslib/characteritzation/dac_scan.py
MainAccesslib/characteritzation/disc_precision_scan.py
MainAccesslib/characteritzation/disc_scan.py
MainAccesslib/characteritzation/ifeed_scan.py
MainAccesslib/characteritzation/logic/__init__.py
MainAccesslib/characteritzation/logic/test_logic.py
MainAccesslib/characteritzation/logic/use_matrix_operations.py
MainAccesslib/equalization/__init__.py
MainAccesslib/equalization/ndarray_operation.py
MainAccesslib/equalization/one_ifeed.py
MainAccesslib/equalization/three_disc_precision.py
MainAccesslib/equalization/two_disc.py
MainAccesslib/equalization/algorithm/__init__.py
MainAccesslib/equalization/algorithm/disc.py
MainAccesslib/equalization/algorithm/disc_precision.py
MainAccesslib/equalization/algorithm/ifeed.py
MainAccesslib-0.0.3.dist-info/METADATA
MainAccesslib-0.0.3.dist-info/WHEEL
MainAccesslib-0.0.3.dist-info/top_level.txt
MainAccesslib-0.0.3.dist-info/RECORD
