Metadata-Version: 2.1
Name: MainAccesslib
Version: 0.0.3
Summary: This lib controls photonai camera.
Home-page: UNKNOWN
License: CC0 1.0 Universal
Platform: UNKNOWN
Classifier: Development Status :: 4 - Beta
Classifier: Programming Language :: Python :: 3
Requires-Python: >=3
Requires-Dist: DDBitConvertAccesslib (==0.1.0)
Requires-Dist: DDBridgeAccesslib (==0.1.0)
Requires-Dist: DDExcelAccesslib (==0.1.1)
Requires-Dist: et-xmlfile (==1.1.0)
Requires-Dist: numpy (==1.23.4)
Requires-Dist: openpyxl (==3.0.10)
Requires-Dist: pandas (==1.5.1)
Requires-Dist: python-dateutil (==2.8.2)
Requires-Dist: pytz (==2022.6)
Requires-Dist: six (==1.16.0)
Requires-Dist: typing-extensions (==4.1.1)
